pynoter/__init__.py
pynoter/fcn/__init__.py
pynoter/fcn/conv_raw.py
pynoter/tests/markup.json
pynoter-0.1.7.data/scripts/py-noter
pynoter-0.1.7.dist-info/DESCRIPTION.rst
pynoter-0.1.7.dist-info/METADATA
pynoter-0.1.7.dist-info/RECORD
pynoter-0.1.7.dist-info/WHEEL
pynoter-0.1.7.dist-info/metadata.json
pynoter-0.1.7.dist-info/top_level.txt
