Metadata-Version: 2.0
Name: pynoter
Version: 0.1.7
Summary: Powerpoint presentations into org or tex files
Home-page: https://github.com/maxrousseau/pynoter
Author: Maxime Rousseau
Author-email: maximerousseau08@gmail.com
License: MIT
Platform: UNKNOWN
Classifier: Programming Language :: Python :: 2.7
Classifier: Topic :: Text Processing :: Markup :: LaTeX
Requires-Dist: python-pptx
